setup.cfg
setup.py
honeywell_thermostat/__init__.py
honeywell_thermostat/main.py
honeywell_thermostat/thermostat.py
honeywell_thermostat.egg-info/PKG-INFO
honeywell_thermostat.egg-info/SOURCES.txt
honeywell_thermostat.egg-info/dependency_links.txt
honeywell_thermostat.egg-info/top_level.txt