Metadata-Version: 1.1
Name: honeywell-thermostat
Version: 1.1.12
Summary: Python API for Honeywell thermostats
Home-page: https://github.com/jorythompson/thermostat
Author: Jordan Thompson
Author-email: Jordan@ThompCo.com
License: MIT
Download-URL: https://github.com/jorythompson/thermostat
Keywords: develoment tools
Platform: UNKNOWN
Classifier: Development Status :: 3 - Alpha
Classifier: Intended Audience :: Developers
Classifier: Topic :: Software Development :: Build Tools
Classifier: License :: OSI Approved :: MIT License
Classifier: Programming Language :: Python :: 2
Classifier: Programming Language :: Python :: 2.6
Classifier: Programming Language :: Python :: 2.7
